{
    "account": [
        { 
            "id": 1,
            "account_id": 1,
            "account_login_id": "111",
            "account_name": "山田太郎１",
            "account_kana": "ヤマダタロウ",
            "belong_name": "開発部",
            "account_authority_type": 1,
            "memo": "",
            "created_at": "2023-11-11 00:00:00",
            "updated_at": "2023-11-11 00:00:00",
            "deleted_at": null
        },
        { 
            "id": 2,
            "account_id": 2,
            "account_login_id": "222",
            "account_name": "鈴木花子2",
            "account_kana": "スズキハナコ",
            "belong_name": "営業部",
            "account_authority_type": 2,
            "memo": "",
            "created_at": "2023-11-11 00:00:00",
            "updated_at": "2023-11-11 00:00:00",
            "deleted_at": null
        }
    ],
    "profile": { "name": "typicode" }
}
